README.md
setup.py
kinkit.egg-info/PKG-INFO
kinkit.egg-info/SOURCES.txt
kinkit.egg-info/dependency_links.txt
kinkit.egg-info/top_level.txt
wu/__init__.py
wu/wy.py